TestToolsMK/VERSION
TestToolsMK/__init__.py
TestToolsMK/collections_keywords.py
TestToolsMK/csv_keywords.py
TestToolsMK/image_pillow_keywords.py
TestToolsMK/logger_extension_keywords.py
TestToolsMK/robot_instances.py
TestToolsMK/selenium_extensions_keywords.py
TestToolsMK/sql_keywords.py
TestToolsMK/timers_keywords.py
TestToolsMK/utils.py
robotframework_MarcinKoperski-1.2.0.15.dist-info/LICENSE
robotframework_MarcinKoperski-1.2.0.15.dist-info/METADATA
robotframework_MarcinKoperski-1.2.0.15.dist-info/WHEEL
robotframework_MarcinKoperski-1.2.0.15.dist-info/top_level.txt
robotframework_MarcinKoperski-1.2.0.15.dist-info/RECORD
